nintynine_boundaries/__init__.py
nintynine_boundaries/data/LU/6/relation_3659532_condominium_lëtzebuerg_deutschland/relation_3659532_condominium_lëtzebuerg_deutschland.geojson.zip
nintynine_boundaries/data/LU/6/relation_3659532_condominium_lëtzebuerg_deutschland/relation_3659532_condominium_lëtzebuerg_deutschland_land.geojson.zip
nintynine_boundaries/make_boundary.py
nintynine_boundaries/utils.py
nintynine_boundaries-0.3.1.dist-info/METADATA
nintynine_boundaries-0.3.1.dist-info/WHEEL
nintynine_boundaries-0.3.1.dist-info/entry_points.txt
nintynine_boundaries-0.3.1.dist-info/licenses/LICENSE
nintynine_boundaries-0.3.1.dist-info/RECORD
