Metadata-Version: 2.4
Name: nintynine-boundaries
Version: 0.3.1
Summary: Generate administrative boundaries with OpenStreetMap and Overpass
License: MIT
License-File: LICENSE
Keywords: osm,openstreetmap,boundaries,geospatial,gis,overpass
Author: Timothy Ellersiek
Author-email: merusame@gmail.com
Requires-Python: >=3.10,<4.0
Classifier: Development Status :: 3 - Alpha
Classifier: Intended Audience :: Developers
Classifier: Intended Audience :: Science/Research
Classifier: License :: OSI Approved :: MIT License
Classifier: Programming Language :: Python :: 3
Classifier: Programming Language :: Python :: 3.10
Classifier: Programming Language :: Python :: 3.11
Classifier: Programming Language :: Python :: 3.12
Classifier: Programming Language :: Python :: 3.13
Classifier: Programming Language :: Python :: 3.14
Classifier: Topic :: Scientific/Engineering :: GIS
Classifier: Topic :: Utilities
Requires-Dist: Rtree (>=1.3.0,<2.0.0)
Requires-Dist: geopandas (>=1.0.0,<2.0.0)
Requires-Dist: numpy (>=2.0.0,<3.0.0)
Requires-Dist: osm2geojson (>=0.3.1,<0.4.0)
Requires-Dist: pandas (>=2.0.0,<3.0.0)
Requires-Dist: pyarrow (>=18.0.0,<19.0.0)
Requires-Dist: requests (>=2.31.0,<3.0.0)
Requires-Dist: tqdm (>=4.66.0,<5.0.0)
Project-URL: Homepage, https://99boundaries.com
Project-URL: Repository, https://github.com/timmccauley/nintynine-boundaries
